qcedu/__init__.py
qcedu/_imports_.py
qcedu/appheader.py
qcedu/appnavbarbrand.py
qcedu/appsidebar.py
qcedu/appsidebarform.py
qcedu/appsidebarheader.py
qcedu/appsidebarnav.py
qcedu/datalist.py
qcedu/eduside.py
qcedu/first.py
qcedu/metadata.json
qcedu/package-info.json
qcedu/qcedu.min.js
qcedu/qcedu.min.js.map
qcedu/searchinput.py
qcedu-0.0.1.dist-info/LICENSE
qcedu-0.0.1.dist-info/METADATA
qcedu-0.0.1.dist-info/WHEEL
qcedu-0.0.1.dist-info/top_level.txt
qcedu-0.0.1.dist-info/RECORD
