Metadata-Version: 2.1
Name: qcedu
Version: 0.0.1
Summary: QCArchive Education
Home-page: UNKNOWN
Author: yuweixie <yuweix@vt.edu>
Author-email: UNKNOWN
License: MIT
Platform: UNKNOWN
